modlogger/__init__.py
modlogger/mod_logger.py
modlogger-1.0.0.dist-info/LICENSE
modlogger-1.0.0.dist-info/METADATA
modlogger-1.0.0.dist-info/WHEEL
modlogger-1.0.0.dist-info/top_level.txt
modlogger-1.0.0.dist-info/RECORD
