Metadata-Version: 2.1
Name: modlogger
Version: 1.0.0
Summary: a easy logger package
Home-page: https://gitlab.com/ouroporos/modlogger
Author: ouroporos
Author-email: ouroporosgod@gmail.com
License: UNKNOWN
Platform: UNKNOWN
Classifier: Programming Language :: Python :: 3
Classifier: License :: OSI Approved :: MIT License
Classifier: Operating System :: OS Independent
